hlatypingtools/__init__.py
hlatypingtools/data/data.pickle.aes
hlatypingtools/decrypt_file.py
hlatypingtools/get_info.py
hlatypingtools-1.0.8.1.dist-info/WHEEL
hlatypingtools-1.0.8.1.dist-info/METADATA
hlatypingtools-1.0.8.1.dist-info/RECORD
