Metadata-Version: 2.1
Name: hlatypingtools
Version: 1.0.8.1
Summary: 
Author: JasonMendoza2008
Author-email: lhotteromain@gmail.com
Requires-Python: >=3.10,<4.0
Classifier: Programming Language :: Python :: 3
Classifier: Programming Language :: Python :: 3.10
Classifier: Programming Language :: Python :: 3.11
Requires-Dist: openpyxl (>=3.1.2,<4.0.0)
Requires-Dist: pandas (>=2.0.0,<3.0.0)
Requires-Dist: pandas-stubs (>=2.0.0.230412,<3.0.0.0)
Requires-Dist: pyaescrypt (>=6.0.0,<7.0.0)
